{
	"name": "2_nycrawratecode",
	"properties": {
		"linkedServiceName": {
			"referenceName": "azrawdatalakeash",
			"type": "LinkedServiceReference"
		},
		"folder": {
			"name": "2_RawToCurated/Raw/Reference"
		},
		"annotations": [],
		"type": "Parquet",
		"typeProperties": {
			"location": {
				"type": "AzureBlobFSLocation",
				"folderPath": "nyctaxi-raw-df/reference/rate-code",
				"fileSystem": "nyctaxi"
			},
			"compressionCodec": "snappy"
		},
		"schema": []
	},
	"type": "Microsoft.Synapse/workspaces/datasets"
}